{
    "home.html": [
        {
            "operation": "PASTE",
            "lines": 35,
            "keyStrokeTimeStamp": "Thu Jul 22 2021 12:58:53",
            "keyStrokeInfo": "<!DOCTYPE html>\r\n<html lang=\"en\">\r\n<head>\r\n  <title>Bootstrap Example</title>\r\n  <meta charset=\"utf-8\">\r\n  <meta name=\"viewport\" content=\"width=device-width, initial-scale=1\">\r\n  <link rel=\"stylesheet\" href=\"https://maxcdn.bootstrapcdn.com/bootstrap/4.5.2/css/bootstrap.min.css\">\r\n  <script src=\"https://ajax.googleapis.com/ajax/libs/jquery/3.5.1/jquery.min.js\"></script>\r\n  <script src=\"https://cdnjs.cloudflare.com/ajax/libs/popper.js/1.16.0/umd/popper.min.js\"></script>\r\n  <script src=\"https://maxcdn.bootstrapcdn.com/bootstrap/4.5.2/js/bootstrap.min.js\"></script>\r\n</head>\r\n<body>\r\n\r\n<div class=\"container\">\r\n  <h2>Stacked form</h2>\r\n  <form action=\"/action_page.php\">\r\n    <div class=\"form-group\">\r\n      <label for=\"email\">Email:</label>\r\n      <input type=\"email\" class=\"form-control\" id=\"email\" placeholder=\"Enter email\" name=\"email\">\r\n    </div>\r\n    <div class=\"form-group\">\r\n      <label for=\"pwd\">Password:</label>\r\n      <input type=\"password\" class=\"form-control\" id=\"pwd\" placeholder=\"Enter password\" name=\"pswd\">\r\n    </div>\r\n    <div class=\"form-group form-check\">\r\n      <label class=\"form-check-label\">\r\n        <input class=\"form-check-input\" type=\"checkbox\" name=\"remember\"> Remember me\r\n      </label>\r\n    </div>\r\n    <button type=\"submit\" class=\"btn btn-primary\">Submit</button>\r\n  </form>\r\n</div>\r\n\r\n</body>\r\n</html>\r\n",
            "position": "1,1"
        },
        {
            "operation": "DELETE",
            "lines": 0,
            "keyStrokeTimeStamp": "Thu Jul 22 2021 12:58:59",
            "keyStrokeInfo": "",
            "position": "4,10"
        },
        {
            "operation": "TYPED",
            "lines": 0,
            "keyStrokeTimeStamp": "Thu Jul 22 2021 12:59:01",
            "keyStrokeInfo": "P",
            "position": "4,10"
        },
        {
            "operation": "TYPED",
            "lines": 0,
            "keyStrokeTimeStamp": "Thu Jul 22 2021 12:59:02",
            "keyStrokeInfo": "r",
            "position": "4,11"
        },
        {
            "operation": "TYPED",
            "lines": 0,
            "keyStrokeTimeStamp": "Thu Jul 22 2021 12:59:02",
            "keyStrokeInfo": "o",
            "position": "4,12"
        },
        {
            "operation": "TYPED",
            "lines": 0,
            "keyStrokeTimeStamp": "Thu Jul 22 2021 12:59:03",
            "keyStrokeInfo": "d",
            "position": "4,13"
        },
        {
            "operation": "TYPED",
            "lines": 0,
            "keyStrokeTimeStamp": "Thu Jul 22 2021 12:59:03",
            "keyStrokeInfo": "u",
            "position": "4,14"
        },
        {
            "operation": "TYPED",
            "lines": 0,
            "keyStrokeTimeStamp": "Thu Jul 22 2021 12:59:04",
            "keyStrokeInfo": "c",
            "position": "4,15"
        },
        {
            "operation": "TYPED",
            "lines": 0,
            "keyStrokeTimeStamp": "Thu Jul 22 2021 12:59:04",
            "keyStrokeInfo": "t",
            "position": "4,16"
        },
        {
            "operation": "TYPED",
            "lines": 0,
            "keyStrokeTimeStamp": "Thu Jul 22 2021 12:59:05",
            "keyStrokeInfo": " ",
            "position": "4,17"
        },
        {
            "operation": "TYPED",
            "lines": 0,
            "keyStrokeTimeStamp": "Thu Jul 22 2021 12:59:05",
            "keyStrokeInfo": "C",
            "position": "4,18"
        },
        {
            "operation": "TYPED",
            "lines": 0,
            "keyStrokeTimeStamp": "Thu Jul 22 2021 12:59:06",
            "keyStrokeInfo": "a",
            "position": "4,19"
        },
        {
            "operation": "PASTE",
            "lines": 1,
            "keyStrokeTimeStamp": "Thu Jul 22 2021 12:59:09",
            "keyStrokeInfo": "Catalogue",
            "position": "4,18"
        },
        {
            "operation": "DELETE",
            "lines": 0,
            "keyStrokeTimeStamp": "Thu Jul 22 2021 12:59:21",
            "keyStrokeInfo": "",
            "position": "15,7"
        },
        {
            "operation": "TYPED",
            "lines": 0,
            "keyStrokeTimeStamp": "Thu Jul 22 2021 12:59:22",
            "keyStrokeInfo": "P",
            "position": "15,7"
        },
        {
            "operation": "TYPED",
            "lines": 0,
            "keyStrokeTimeStamp": "Thu Jul 22 2021 12:59:24",
            "keyStrokeInfo": "r",
            "position": "15,8"
        },
        {
            "operation": "TYPED",
            "lines": 0,
            "keyStrokeTimeStamp": "Thu Jul 22 2021 12:59:24",
            "keyStrokeInfo": "o",
            "position": "15,9"
        },
        {
            "operation": "TYPED",
            "lines": 0,
            "keyStrokeTimeStamp": "Thu Jul 22 2021 12:59:25",
            "keyStrokeInfo": "Product",
            "position": "15,7"
        },
        {
            "operation": "TYPED",
            "lines": 0,
            "keyStrokeTimeStamp": "Thu Jul 22 2021 12:59:26",
            "keyStrokeInfo": " ",
            "position": "15,14"
        },
        {
            "operation": "TYPED",
            "lines": 0,
            "keyStrokeTimeStamp": "Thu Jul 22 2021 12:59:26",
            "keyStrokeInfo": "C",
            "position": "15,15"
        },
        {
            "operation": "DELETE",
            "lines": 0,
            "keyStrokeTimeStamp": "Thu Jul 22 2021 12:59:27",
            "keyStrokeInfo": "",
            "position": "15,15"
        },
        {
            "operation": "TYPED",
            "lines": 0,
            "keyStrokeTimeStamp": "Thu Jul 22 2021 12:59:28",
            "keyStrokeInfo": "c",
            "position": "15,15"
        },
        {
            "operation": "TYPED",
            "lines": 0,
            "keyStrokeTimeStamp": "Thu Jul 22 2021 12:59:28",
            "keyStrokeInfo": "a",
            "position": "15,16"
        },
        {
            "operation": "TYPED",
            "lines": 0,
            "keyStrokeTimeStamp": "Thu Jul 22 2021 12:59:29",
            "keyStrokeInfo": "t",
            "position": "15,17"
        },
        {
            "operation": "PASTE",
            "lines": 1,
            "keyStrokeTimeStamp": "Thu Jul 22 2021 12:59:30",
            "keyStrokeInfo": "Catalogue",
            "position": "15,15"
        },
        {
            "operation": "TYPED",
            "lines": 0,
            "keyStrokeTimeStamp": "Thu Jul 22 2021 12:59:42",
            "keyStrokeInfo": "P",
            "position": "18,26"
        },
        {
            "operation": "DELETE",
            "lines": 0,
            "keyStrokeTimeStamp": "Thu Jul 22 2021 12:59:52",
            "keyStrokeInfo": "",
            "position": "18,26"
        },
        {
            "operation": "TYPED",
            "lines": 0,
            "keyStrokeTimeStamp": "Thu Jul 22 2021 12:59:53",
            "keyStrokeInfo": "Name",
            "position": "18,26"
        },
        {
            "operation": "TYPED",
            "lines": 0,
            "keyStrokeTimeStamp": "Thu Jul 22 2021 13:00:44",
            "keyStrokeInfo": "text",
            "position": "19,20"
        },
        {
            "operation": "DELETE",
            "lines": 0,
            "keyStrokeTimeStamp": "Thu Jul 22 2021 13:00:54",
            "keyStrokeInfo": "",
            "position": "19,51"
        },
        {
            "operation": "TYPED",
            "lines": 0,
            "keyStrokeTimeStamp": "Thu Jul 22 2021 13:00:54",
            "keyStrokeInfo": "n",
            "position": "19,51"
        },
        {
            "operation": "TYPED",
            "lines": 0,
            "keyStrokeTimeStamp": "Thu Jul 22 2021 13:00:54",
            "keyStrokeInfo": "a",
            "position": "19,52"
        },
        {
            "operation": "TYPED",
            "lines": 0,
            "keyStrokeTimeStamp": "Thu Jul 22 2021 13:00:54",
            "keyStrokeInfo": "m",
            "position": "19,53"
        },
        {
            "operation": "TYPED",
            "lines": 0,
            "keyStrokeTimeStamp": "Thu Jul 22 2021 13:00:55",
            "keyStrokeInfo": "w",
            "position": "19,54"
        },
        {
            "operation": "DELETE",
            "lines": 0,
            "keyStrokeTimeStamp": "Thu Jul 22 2021 13:00:56",
            "keyStrokeInfo": "",
            "position": "19,54"
        },
        {
            "operation": "TYPED",
            "lines": 0,
            "keyStrokeTimeStamp": "Thu Jul 22 2021 13:00:56",
            "keyStrokeInfo": "e",
            "position": "19,54"
        },
        {
            "operation": "TYPED",
            "lines": 0,
            "keyStrokeTimeStamp": "Thu Jul 22 2021 13:01:01",
            "keyStrokeInfo": "P",
            "position": "19,70"
        },
        {
            "operation": "TYPED",
            "lines": 0,
            "keyStrokeTimeStamp": "Thu Jul 22 2021 13:01:02",
            "keyStrokeInfo": "r",
            "position": "19,71"
        },
        {
            "operation": "TYPED",
            "lines": 0,
            "keyStrokeTimeStamp": "Thu Jul 22 2021 13:01:03",
            "keyStrokeInfo": "o",
            "position": "19,72"
        },
        {
            "operation": "TYPED",
            "lines": 0,
            "keyStrokeTimeStamp": "Thu Jul 22 2021 13:01:03",
            "keyStrokeInfo": "d",
            "position": "19,73"
        },
        {
            "operation": "TYPED",
            "lines": 0,
            "keyStrokeTimeStamp": "Thu Jul 22 2021 13:01:03",
            "keyStrokeInfo": "u",
            "position": "19,74"
        },
        {
            "operation": "TYPED",
            "lines": 0,
            "keyStrokeTimeStamp": "Thu Jul 22 2021 13:01:04",
            "keyStrokeInfo": "c",
            "position": "19,75"
        },
        {
            "operation": "TYPED",
            "lines": 0,
            "keyStrokeTimeStamp": "Thu Jul 22 2021 13:01:04",
            "keyStrokeInfo": " ",
            "position": "19,76"
        },
        {
            "operation": "TYPED",
            "lines": 0,
            "keyStrokeTimeStamp": "Thu Jul 22 2021 13:01:04",
            "keyStrokeInfo": "t",
            "position": "19,77"
        },
        {
            "operation": "DELETE",
            "lines": 0,
            "keyStrokeTimeStamp": "Thu Jul 22 2021 13:01:05",
            "keyStrokeInfo": "",
            "position": "19,77"
        },
        {
            "operation": "DELETE",
            "lines": 0,
            "keyStrokeTimeStamp": "Thu Jul 22 2021 13:01:05",
            "keyStrokeInfo": "",
            "position": "19,76"
        },
        {
            "operation": "TYPED",
            "lines": 0,
            "keyStrokeTimeStamp": "Thu Jul 22 2021 13:01:05",
            "keyStrokeInfo": "t",
            "position": "19,76"
        },
        {
            "operation": "TYPED",
            "lines": 0,
            "keyStrokeTimeStamp": "Thu Jul 22 2021 13:01:05",
            "keyStrokeInfo": " ",
            "position": "19,77"
        },
        {
            "operation": "TYPED",
            "lines": 0,
            "keyStrokeTimeStamp": "Thu Jul 22 2021 13:01:06",
            "keyStrokeInfo": "n",
            "position": "19,78"
        },
        {
            "operation": "TYPED",
            "lines": 0,
            "keyStrokeTimeStamp": "Thu Jul 22 2021 13:01:06",
            "keyStrokeInfo": "a",
            "position": "19,79"
        },
        {
            "operation": "TYPED",
            "lines": 0,
            "keyStrokeTimeStamp": "Thu Jul 22 2021 13:01:06",
            "keyStrokeInfo": "m",
            "position": "19,80"
        },
        {
            "operation": "TYPED",
            "lines": 0,
            "keyStrokeTimeStamp": "Thu Jul 22 2021 13:01:06",
            "keyStrokeInfo": "e",
            "position": "19,81"
        },
        {
            "operation": "TYPED",
            "lines": 0,
            "keyStrokeTimeStamp": "Thu Jul 22 2021 13:01:24",
            "keyStrokeInfo": "n",
            "position": "19,90"
        },
        {
            "operation": "TYPED",
            "lines": 0,
            "keyStrokeTimeStamp": "Thu Jul 22 2021 13:01:24",
            "keyStrokeInfo": "a",
            "position": "19,91"
        },
        {
            "operation": "TYPED",
            "lines": 0,
            "keyStrokeTimeStamp": "Thu Jul 22 2021 13:01:24",
            "keyStrokeInfo": "m",
            "position": "19,92"
        },
        {
            "operation": "TYPED",
            "lines": 0,
            "keyStrokeTimeStamp": "Thu Jul 22 2021 13:01:24",
            "keyStrokeInfo": "e",
            "position": "19,93"
        },
        {
            "operation": "TYPED",
            "lines": 0,
            "keyStrokeTimeStamp": "Thu Jul 22 2021 13:01:33",
            "keyStrokeInfo": "\r\n    ",
            "position": "20,11"
        },
        {
            "operation": "PASTE",
            "lines": 4,
            "keyStrokeTimeStamp": "Thu Jul 22 2021 13:01:34",
            "keyStrokeInfo": "<div class=\"form-group\">\r\n      <label for=\"email\">Name:</label>\r\n      <input type=\"text\" class=\"form-control\" id=\"name\" placeholder=\"Product name\" name=\"name\">\r\n    </div>",
            "position": "21,5"
        },
        {
            "operation": "PASTE",
            "lines": 1,
            "keyStrokeTimeStamp": "Thu Jul 22 2021 13:01:44",
            "keyStrokeInfo": "Description",
            "position": "22,26"
        },
        {
            "operation": "PASTE",
            "lines": 1,
            "keyStrokeTimeStamp": "Thu Jul 22 2021 13:01:46",
            "keyStrokeInfo": "Description",
            "position": "23,78"
        },
        {
            "operation": "PASTE",
            "lines": 1,
            "keyStrokeTimeStamp": "Thu Jul 22 2021 13:01:52",
            "keyStrokeInfo": "Description",
            "position": "23,97"
        },
        {
            "operation": "PASTE",
            "lines": 1,
            "keyStrokeTimeStamp": "Thu Jul 22 2021 13:01:54",
            "keyStrokeInfo": "Description",
            "position": "23,51"
        },
        {
            "operation": "TYPED",
            "lines": 0,
            "keyStrokeTimeStamp": "Thu Jul 22 2021 13:01:58",
            "keyStrokeInfo": "\r\n    ",
            "position": "24,11"
        },
        {
            "operation": "DELETE",
            "lines": 0,
            "keyStrokeTimeStamp": "Thu Jul 22 2021 13:02:08",
            "keyStrokeInfo": "\r\n    ",
            "position": "24,11"
        },
        {
            "operation": "PASTE",
            "lines": 4,
            "keyStrokeTimeStamp": "Thu Jul 22 2021 13:02:08",
            "keyStrokeInfo": "<div class=\"form-group\">\r\n      <label for=\"email\">Descriptione:</label>\r\n      <input type=\"text\" class=\"form-control\" id=\"Description\" placeholder=\"Product Description\" name=\"Description\">\r\n    </div>",
            "position": "25,5"
        },
        {
            "operation": "PASTE",
            "lines": 4,
            "keyStrokeTimeStamp": "Thu Jul 22 2021 13:04:02",
            "keyStrokeInfo": "<div class=\"form-group\">\r\n      <label for=\"email\">Descriptione:</label>\r\n      <input type=\"text\" class=\"form-control\" id=\"Description\" placeholder=\"Product Description\" name=\"Description\">\r\n    </div>",
            "position": "18,19"
        },
        {
            "operation": "TYPED",
            "lines": 0,
            "keyStrokeTimeStamp": "Thu Jul 22 2021 13:04:03",
            "keyStrokeInfo": "email",
            "position": "18,19"
        },
        {
            "operation": "TYPED",
            "lines": 0,
            "keyStrokeTimeStamp": "Thu Jul 22 2021 13:04:07",
            "keyStrokeInfo": "\r\n    ",
            "position": "28,11"
        },
        {
            "operation": "PASTE",
            "lines": 4,
            "keyStrokeTimeStamp": "Thu Jul 22 2021 13:04:08",
            "keyStrokeInfo": "<div class=\"form-group\">\r\n      <label for=\"email\">Descriptione:</label>\r\n      <input type=\"text\" class=\"form-control\" id=\"Description\" placeholder=\"Product Description\" name=\"Description\">\r\n    </div>",
            "position": "29,5"
        },
        {
            "operation": "TYPED",
            "lines": 0,
            "keyStrokeTimeStamp": "Thu Jul 22 2021 13:04:11",
            "keyStrokeInfo": "n",
            "position": "18,19"
        },
        {
            "operation": "TYPED",
            "lines": 0,
            "keyStrokeTimeStamp": "Thu Jul 22 2021 13:04:12",
            "keyStrokeInfo": "a",
            "position": "18,20"
        },
        {
            "operation": "TYPED",
            "lines": 0,
            "keyStrokeTimeStamp": "Thu Jul 22 2021 13:04:12",
            "keyStrokeInfo": "m",
            "position": "18,21"
        },
        {
            "operation": "TYPED",
            "lines": 0,
            "keyStrokeTimeStamp": "Thu Jul 22 2021 13:04:12",
            "keyStrokeInfo": "e",
            "position": "18,22"
        },
        {
            "operation": "DELETE",
            "lines": 0,
            "keyStrokeTimeStamp": "Thu Jul 22 2021 13:04:17",
            "keyStrokeInfo": "",
            "position": "22,38"
        },
        {
            "operation": "TYPED",
            "lines": 0,
            "keyStrokeTimeStamp": "Thu Jul 22 2021 13:04:19",
            "keyStrokeInfo": ":",
            "position": "22,38"
        },
        {
            "operation": "DELETE",
            "lines": 0,
            "keyStrokeTimeStamp": "Thu Jul 22 2021 13:04:21",
            "keyStrokeInfo": "",
            "position": "22,37"
        },
        {
            "operation": "PASTE",
            "lines": 1,
            "keyStrokeTimeStamp": "Thu Jul 22 2021 13:04:25",
            "keyStrokeInfo": "Description",
            "position": "22,19"
        },
        {
            "operation": "TYPED",
            "lines": 0,
            "keyStrokeTimeStamp": "Thu Jul 22 2021 13:04:30",
            "keyStrokeInfo": "P",
            "position": "26,26"
        },
        {
            "operation": "TYPED",
            "lines": 0,
            "keyStrokeTimeStamp": "Thu Jul 22 2021 13:04:30",
            "keyStrokeInfo": "r",
            "position": "26,27"
        },
        {
            "operation": "TYPED",
            "lines": 0,
            "keyStrokeTimeStamp": "Thu Jul 22 2021 13:04:31",
            "keyStrokeInfo": "i",
            "position": "26,28"
        },
        {
            "operation": "TYPED",
            "lines": 0,
            "keyStrokeTimeStamp": "Thu Jul 22 2021 13:04:31",
            "keyStrokeInfo": "c",
            "position": "26,29"
        },
        {
            "operation": "TYPED",
            "lines": 0,
            "keyStrokeTimeStamp": "Thu Jul 22 2021 13:04:32",
            "keyStrokeInfo": "e",
            "position": "26,30"
        },
        {
            "operation": "TYPED",
            "lines": 0,
            "keyStrokeTimeStamp": "Thu Jul 22 2021 13:04:36",
            "keyStrokeInfo": "Price",
            "position": "26,19"
        },
        {
            "operation": "TYPED",
            "lines": 0,
            "keyStrokeTimeStamp": "Thu Jul 22 2021 13:04:40",
            "keyStrokeInfo": "Price",
            "position": "27,51"
        },
        {
            "operation": "TYPED",
            "lines": 0,
            "keyStrokeTimeStamp": "Thu Jul 22 2021 13:04:41",
            "keyStrokeInfo": "Price",
            "position": "27,98"
        },
        {
            "operation": "TYPED",
            "lines": 0,
            "keyStrokeTimeStamp": "Thu Jul 22 2021 13:04:43",
            "keyStrokeInfo": "Price",
            "position": "27,79"
        },
        {
            "operation": "TYPED",
            "lines": 0,
            "keyStrokeTimeStamp": "Thu Jul 22 2021 13:05:33",
            "keyStrokeInfo": "Price",
            "position": "30,26"
        },
        {
            "operation": "DELETE",
            "lines": 0,
            "keyStrokeTimeStamp": "Thu Jul 22 2021 13:05:35",
            "keyStrokeInfo": "",
            "position": "30,30"
        },
        {
            "operation": "DELETE",
            "lines": 0,
            "keyStrokeTimeStamp": "Thu Jul 22 2021 13:05:35",
            "keyStrokeInfo": "",
            "position": "30,29"
        },
        {
            "operation": "DELETE",
            "lines": 0,
            "keyStrokeTimeStamp": "Thu Jul 22 2021 13:05:35",
            "keyStrokeInfo": "",
            "position": "30,28"
        },
        {
            "operation": "DELETE",
            "lines": 0,
            "keyStrokeTimeStamp": "Thu Jul 22 2021 13:05:36",
            "keyStrokeInfo": "",
            "position": "30,27"
        },
        {
            "operation": "DELETE",
            "lines": 0,
            "keyStrokeTimeStamp": "Thu Jul 22 2021 13:05:36",
            "keyStrokeInfo": "",
            "position": "30,26"
        },
        {
            "operation": "TYPED",
            "lines": 0,
            "keyStrokeTimeStamp": "Thu Jul 22 2021 13:05:37",
            "keyStrokeInfo": "M",
            "position": "30,26"
        },
        {
            "operation": "TYPED",
            "lines": 0,
            "keyStrokeTimeStamp": "Thu Jul 22 2021 13:05:38",
            "keyStrokeInfo": "F",
            "position": "30,27"
        },
        {
            "operation": "TYPED",
            "lines": 0,
            "keyStrokeTimeStamp": "Thu Jul 22 2021 13:05:38",
            "keyStrokeInfo": "D",
            "position": "30,28"
        },
        {
            "operation": "TYPED",
            "lines": 0,
            "keyStrokeTimeStamp": "Thu Jul 22 2021 13:05:44",
            "keyStrokeInfo": "MFD",
            "position": "30,19"
        },
        {
            "operation": "TYPED",
            "lines": 0,
            "keyStrokeTimeStamp": "Thu Jul 22 2021 13:05:50",
            "keyStrokeInfo": "MFD",
            "position": "31,51"
        },
        {
            "operation": "TYPED",
            "lines": 0,
            "keyStrokeTimeStamp": "Thu Jul 22 2021 13:05:53",
            "keyStrokeInfo": "MFD",
            "position": "31,77"
        },
        {
            "operation": "TYPED",
            "lines": 0,
            "keyStrokeTimeStamp": "Thu Jul 22 2021 13:05:55",
            "keyStrokeInfo": "MFD",
            "position": "31,88"
        },
        {
            "operation": "DELETE",
            "lines": 8,
            "keyStrokeTimeStamp": "Thu Jul 22 2021 13:06:07",
            "keyStrokeInfo": "",
            "position": "34,5"
        },
        {
            "operation": "TYPED",
            "lines": 0,
            "keyStrokeTimeStamp": "Thu Jul 22 2021 13:06:13",
            "keyStrokeInfo": "\r\n    ",
            "position": "32,11"
        },
        {
            "operation": "PASTE",
            "lines": 4,
            "keyStrokeTimeStamp": "Thu Jul 22 2021 13:06:13",
            "keyStrokeInfo": "<div class=\"form-group\">\r\n      <label for=\"MFD\">MFD:</label>\r\n      <input type=\"text\" class=\"form-control\" id=\"MFD\" placeholder=\"Product MFD\" name=\"MFD\">\r\n    </div>",
            "position": "33,5"
        },
        {
            "operation": "PASTE",
            "lines": 1,
            "keyStrokeTimeStamp": "Thu Jul 22 2021 13:06:23",
            "keyStrokeInfo": "Expiry Date",
            "position": "34,19"
        },
        {
            "operation": "PASTE",
            "lines": 1,
            "keyStrokeTimeStamp": "Thu Jul 22 2021 13:06:24",
            "keyStrokeInfo": "Expiry Date",
            "position": "34,32"
        },
        {
            "operation": "PASTE",
            "lines": 1,
            "keyStrokeTimeStamp": "Thu Jul 22 2021 13:06:32",
            "keyStrokeInfo": "Expiry Date",
            "position": "35,51"
        },
        {
            "operation": "PASTE",
            "lines": 1,
            "keyStrokeTimeStamp": "Thu Jul 22 2021 13:06:33",
            "keyStrokeInfo": "Expiry Date",
            "position": "35,85"
        },
        {
            "operation": "PASTE",
            "lines": 1,
            "keyStrokeTimeStamp": "Thu Jul 22 2021 13:06:35",
            "keyStrokeInfo": "Expiry Date",
            "position": "35,104"
        },
        {
            "operation": "PASTE",
            "lines": 2,
            "keyStrokeTimeStamp": "Thu Jul 22 2021 13:08:44",
            "keyStrokeInfo": "<label class=\"form-label\" for=\"customFile\">Default file input example</label>\r\n<input type=\"file\" class=\"form-control\" id=\"customFile\" />",
            "position": "38,5"
        },
        {
            "operation": "PASTE",
            "lines": 1,
            "keyStrokeTimeStamp": "Thu Jul 22 2021 13:08:49",
            "keyStrokeInfo": "<div class=\"form-group\">",
            "position": "37,1"
        },
        {
            "operation": "TYPED",
            "lines": 0,
            "keyStrokeTimeStamp": "Thu Jul 22 2021 13:08:52",
            "keyStrokeInfo": "    ",
            "position": "37,1"
        },
        {
            "operation": "TYPED",
            "lines": 0,
            "keyStrokeTimeStamp": "Thu Jul 22 2021 13:08:55",
            "keyStrokeInfo": "    ",
            "position": "38,5"
        },
        {
            "operation": "TYPED",
            "lines": 0,
            "keyStrokeTimeStamp": "Thu Jul 22 2021 13:08:57",
            "keyStrokeInfo": "   ",
            "position": "39,2"
        },
        {
            "operation": "TYPED",
            "lines": 0,
            "keyStrokeTimeStamp": "Thu Jul 22 2021 13:09:00",
            "keyStrokeInfo": "<",
            "position": "39,5"
        },
        {
            "operation": "TYPED",
            "lines": 0,
            "keyStrokeTimeStamp": "Thu Jul 22 2021 13:09:01",
            "keyStrokeInfo": "   ",
            "position": "39,6"
        },
        {
            "operation": "DELETE",
            "lines": 0,
            "keyStrokeTimeStamp": "Thu Jul 22 2021 13:09:02",
            "keyStrokeInfo": "",
            "position": "39,8"
        },
        {
            "operation": "DELETE",
            "lines": 0,
            "keyStrokeTimeStamp": "Thu Jul 22 2021 13:09:02",
            "keyStrokeInfo": "",
            "position": "39,7"
        },
        {
            "operation": "DELETE",
            "lines": 0,
            "keyStrokeTimeStamp": "Thu Jul 22 2021 13:09:02",
            "keyStrokeInfo": "",
            "position": "39,6"
        },
        {
            "operation": "DELETE",
            "lines": 0,
            "keyStrokeTimeStamp": "Thu Jul 22 2021 13:09:03",
            "keyStrokeInfo": "",
            "position": "39,5"
        },
        {
            "operation": "DELETE",
            "lines": 0,
            "keyStrokeTimeStamp": "Thu Jul 22 2021 13:09:03",
            "keyStrokeInfo": "",
            "position": "39,4"
        },
        {
            "operation": "DELETE",
            "lines": 0,
            "keyStrokeTimeStamp": "Thu Jul 22 2021 13:09:03",
            "keyStrokeInfo": "",
            "position": "39,3"
        },
        {
            "operation": "DELETE",
            "lines": 0,
            "keyStrokeTimeStamp": "Thu Jul 22 2021 13:09:03",
            "keyStrokeInfo": "",
            "position": "39,2"
        },
        {
            "operation": "TYPED",
            "lines": 0,
            "keyStrokeTimeStamp": "Thu Jul 22 2021 13:09:04",
            "keyStrokeInfo": "    ",
            "position": "39,1"
        },
        {
            "operation": "TYPED",
            "lines": 0,
            "keyStrokeTimeStamp": "Thu Jul 22 2021 13:09:05",
            "keyStrokeInfo": "    ",
            "position": "39,5"
        },
        {
            "operation": "TYPED",
            "lines": 0,
            "keyStrokeTimeStamp": "Thu Jul 22 2021 13:09:18",
            "keyStrokeInfo": "<",
            "position": "39,67"
        },
        {
            "operation": "TYPED",
            "lines": 0,
            "keyStrokeTimeStamp": "Thu Jul 22 2021 13:09:19",
            "keyStrokeInfo": ">",
            "position": "39,68"
        },
        {
            "operation": "TYPED",
            "lines": 0,
            "keyStrokeTimeStamp": "Thu Jul 22 2021 13:09:21",
            "keyStrokeInfo": "/",
            "position": "39,68"
        },
        {
            "operation": "TYPED",
            "lines": 0,
            "keyStrokeTimeStamp": "Thu Jul 22 2021 13:09:22",
            "keyStrokeInfo": "d",
            "position": "39,69"
        },
        {
            "operation": "TYPED",
            "lines": 0,
            "keyStrokeTimeStamp": "Thu Jul 22 2021 13:09:22",
            "keyStrokeInfo": "i",
            "position": "39,70"
        },
        {
            "operation": "TYPED",
            "lines": 0,
            "keyStrokeTimeStamp": "Thu Jul 22 2021 13:09:22",
            "keyStrokeInfo": "v",
            "position": "39,71"
        },
        {
            "operation": "PASTE",
            "lines": 1,
            "keyStrokeTimeStamp": "Thu Jul 22 2021 13:09:24",
            "keyStrokeInfo": "\r\n        ",
            "position": "39,73"
        },
        {
            "operation": "DELETE",
            "lines": 0,
            "keyStrokeTimeStamp": "Thu Jul 22 2021 13:09:51",
            "keyStrokeInfo": "<",
            "position": "13,1"
        },
        {
            "operation": "TYPED",
            "lines": 0,
            "keyStrokeTimeStamp": "Thu Jul 22 2021 13:09:51",
            "keyStrokeInfo": ">",
            "position": "13,2"
        },
        {
            "operation": "TYPED",
            "lines": 0,
            "keyStrokeTimeStamp": "Thu Jul 22 2021 13:09:52",
            "keyStrokeInfo": "c",
            "position": "13,2"
        },
        {
            "operation": "TYPED",
            "lines": 0,
            "keyStrokeTimeStamp": "Thu Jul 22 2021 13:09:52",
            "keyStrokeInfo": "e",
            "position": "13,3"
        },
        {
            "operation": "TYPED",
            "lines": 0,
            "keyStrokeTimeStamp": "Thu Jul 22 2021 13:09:52",
            "keyStrokeInfo": "n",
            "position": "13,4"
        },
        {
            "operation": "TYPED",
            "lines": 0,
            "keyStrokeTimeStamp": "Thu Jul 22 2021 13:09:53",
            "keyStrokeInfo": "t",
            "position": "13,5"
        },
        {
            "operation": "TYPED",
            "lines": 0,
            "keyStrokeTimeStamp": "Thu Jul 22 2021 13:09:53",
            "keyStrokeInfo": "e",
            "position": "13,6"
        },
        {
            "operation": "TYPED",
            "lines": 0,
            "keyStrokeTimeStamp": "Thu Jul 22 2021 13:09:53",
            "keyStrokeInfo": "r",
            "position": "13,7"
        },
        {
            "operation": "TYPED",
            "lines": 0,
            "keyStrokeTimeStamp": "Thu Jul 22 2021 13:09:54",
            "keyStrokeInfo": "center",
            "position": "13,2"
        },
        {
            "operation": "TYPED",
            "lines": 0,
            "keyStrokeTimeStamp": "Thu Jul 22 2021 13:09:58",
            "keyStrokeInfo": "\r\n  ",
            "position": "42,10"
        },
        {
            "operation": "DELETE",
            "lines": 0,
            "keyStrokeTimeStamp": "Thu Jul 22 2021 13:09:58",
            "keyStrokeInfo": "",
            "position": "43,1"
        },
        {
            "operation": "TYPED",
            "lines": 0,
            "keyStrokeTimeStamp": "Thu Jul 22 2021 13:09:59",
            "keyStrokeInfo": "<",
            "position": "43,1"
        },
        {
            "operation": "TYPED",
            "lines": 0,
            "keyStrokeTimeStamp": "Thu Jul 22 2021 13:09:59",
            "keyStrokeInfo": ">",
            "position": "43,2"
        },
        {
            "operation": "DELETE",
            "lines": 0,
            "keyStrokeTimeStamp": "Thu Jul 22 2021 13:10:01",
            "keyStrokeInfo": "",
            "position": "43,1"
        },
        {
            "operation": "DELETE",
            "lines": 0,
            "keyStrokeTimeStamp": "Thu Jul 22 2021 13:10:03",
            "keyStrokeInfo": "",
            "position": "43,1"
        },
        {
            "operation": "TYPED",
            "lines": 0,
            "keyStrokeTimeStamp": "Thu Jul 22 2021 13:10:07",
            "keyStrokeInfo": "<",
            "position": "45,1"
        },
        {
            "operation": "TYPED",
            "lines": 0,
            "keyStrokeTimeStamp": "Thu Jul 22 2021 13:10:07",
            "keyStrokeInfo": ">",
            "position": "45,2"
        },
        {
            "operation": "TYPED",
            "lines": 0,
            "keyStrokeTimeStamp": "Thu Jul 22 2021 13:10:08",
            "keyStrokeInfo": "c",
            "position": "45,2"
        },
        {
            "operation": "TYPED",
            "lines": 0,
            "keyStrokeTimeStamp": "Thu Jul 22 2021 13:10:09",
            "keyStrokeInfo": "e",
            "position": "45,3"
        },
        {
            "operation": "TYPED",
            "lines": 0,
            "keyStrokeTimeStamp": "Thu Jul 22 2021 13:10:09",
            "keyStrokeInfo": "n",
            "position": "45,4"
        },
        {
            "operation": "TYPED",
            "lines": 0,
            "keyStrokeTimeStamp": "Thu Jul 22 2021 13:10:09",
            "keyStrokeInfo": "t",
            "position": "45,5"
        },
        {
            "operation": "TYPED",
            "lines": 0,
            "keyStrokeTimeStamp": "Thu Jul 22 2021 13:10:09",
            "keyStrokeInfo": "e",
            "position": "45,6"
        },
        {
            "operation": "TYPED",
            "lines": 0,
            "keyStrokeTimeStamp": "Thu Jul 22 2021 13:10:10",
            "keyStrokeInfo": "r",
            "position": "45,7"
        },
        {
            "operation": "TYPED",
            "lines": 0,
            "keyStrokeTimeStamp": "Thu Jul 22 2021 13:10:12",
            "keyStrokeInfo": "/",
            "position": "45,2"
        },
        {
            "operation": "DELETE",
            "lines": 0,
            "keyStrokeTimeStamp": "Thu Jul 22 2021 13:10:22",
            "keyStrokeInfo": "",
            "position": "45,1"
        },
        {
            "operation": "DELETE",
            "lines": 0,
            "keyStrokeTimeStamp": "Thu Jul 22 2021 13:10:26",
            "keyStrokeInfo": "",
            "position": "13,1"
        },
        {
            "operation": "TYPED",
            "lines": 0,
            "keyStrokeTimeStamp": "Thu Jul 22 2021 13:10:33",
            "keyStrokeInfo": "<",
            "position": "15,2"
        },
        {
            "operation": "TYPED",
            "lines": 0,
            "keyStrokeTimeStamp": "Thu Jul 22 2021 13:10:33",
            "keyStrokeInfo": ">",
            "position": "15,3"
        },
        {
            "operation": "TYPED",
            "lines": 0,
            "keyStrokeTimeStamp": "Thu Jul 22 2021 13:10:34",
            "keyStrokeInfo": "c",
            "position": "15,3"
        },
        {
            "operation": "TYPED",
            "lines": 0,
            "keyStrokeTimeStamp": "Thu Jul 22 2021 13:10:35",
            "keyStrokeInfo": "e",
            "position": "15,4"
        },
        {
            "operation": "TYPED",
            "lines": 0,
            "keyStrokeTimeStamp": "Thu Jul 22 2021 13:10:35",
            "keyStrokeInfo": "n",
            "position": "15,5"
        },
        {
            "operation": "TYPED",
            "lines": 0,
            "keyStrokeTimeStamp": "Thu Jul 22 2021 13:10:35",
            "keyStrokeInfo": "t",
            "position": "15,6"
        },
        {
            "operation": "TYPED",
            "lines": 0,
            "keyStrokeTimeStamp": "Thu Jul 22 2021 13:10:35",
            "keyStrokeInfo": "e",
            "position": "15,7"
        },
        {
            "operation": "TYPED",
            "lines": 0,
            "keyStrokeTimeStamp": "Thu Jul 22 2021 13:10:35",
            "keyStrokeInfo": "r",
            "position": "15,8"
        },
        {
            "operation": "TYPED",
            "lines": 0,
            "keyStrokeTimeStamp": "Thu Jul 22 2021 13:10:36",
            "keyStrokeInfo": "center",
            "position": "15,3"
        },
        {
            "operation": "TYPED",
            "lines": 0,
            "keyStrokeTimeStamp": "Thu Jul 22 2021 13:10:39",
            "keyStrokeInfo": "<",
            "position": "15,37"
        },
        {
            "operation": "TYPED",
            "lines": 0,
            "keyStrokeTimeStamp": "Thu Jul 22 2021 13:10:39",
            "keyStrokeInfo": ">",
            "position": "15,38"
        },
        {
            "operation": "TYPED",
            "lines": 0,
            "keyStrokeTimeStamp": "Thu Jul 22 2021 13:10:41",
            "keyStrokeInfo": "/",
            "position": "15,38"
        },
        {
            "operation": "TYPED",
            "lines": 0,
            "keyStrokeTimeStamp": "Thu Jul 22 2021 13:10:41",
            "keyStrokeInfo": "c",
            "position": "15,39"
        },
        {
            "operation": "TYPED",
            "lines": 0,
            "keyStrokeTimeStamp": "Thu Jul 22 2021 13:10:41",
            "keyStrokeInfo": "e",
            "position": "15,40"
        },
        {
            "operation": "TYPED",
            "lines": 0,
            "keyStrokeTimeStamp": "Thu Jul 22 2021 13:10:41",
            "keyStrokeInfo": "n",
            "position": "15,41"
        },
        {
            "operation": "TYPED",
            "lines": 0,
            "keyStrokeTimeStamp": "Thu Jul 22 2021 13:10:41",
            "keyStrokeInfo": "t",
            "position": "15,42"
        },
        {
            "operation": "TYPED",
            "lines": 0,
            "keyStrokeTimeStamp": "Thu Jul 22 2021 13:10:42",
            "keyStrokeInfo": "e",
            "position": "15,43"
        },
        {
            "operation": "TYPED",
            "lines": 0,
            "keyStrokeTimeStamp": "Thu Jul 22 2021 13:10:42",
            "keyStrokeInfo": "r",
            "position": "15,44"
        },
        {
            "operation": "TYPED",
            "lines": 0,
            "keyStrokeTimeStamp": "Thu Jul 22 2021 13:10:58",
            "keyStrokeInfo": "<",
            "position": "13,1"
        },
        {
            "operation": "TYPED",
            "lines": 0,
            "keyStrokeTimeStamp": "Thu Jul 22 2021 13:10:58",
            "keyStrokeInfo": ">",
            "position": "13,2"
        },
        {
            "operation": "TYPED",
            "lines": 0,
            "keyStrokeTimeStamp": "Thu Jul 22 2021 13:10:59",
            "keyStrokeInfo": "b",
            "position": "13,2"
        },
        {
            "operation": "TYPED",
            "lines": 0,
            "keyStrokeTimeStamp": "Thu Jul 22 2021 13:10:59",
            "keyStrokeInfo": "r",
            "position": "13,3"
        },
        {
            "operation": "TYPED",
            "lines": 0,
            "keyStrokeTimeStamp": "Thu Jul 22 2021 13:11:01",
            "keyStrokeInfo": "\r\n",
            "position": "13,5"
        },
        {
            "operation": "TYPED",
            "lines": 0,
            "keyStrokeTimeStamp": "Thu Jul 22 2021 13:11:02",
            "keyStrokeInfo": "<",
            "position": "14,1"
        },
        {
            "operation": "TYPED",
            "lines": 0,
            "keyStrokeTimeStamp": "Thu Jul 22 2021 13:11:02",
            "keyStrokeInfo": ".",
            "position": "14,2"
        },
        {
            "operation": "DELETE",
            "lines": 0,
            "keyStrokeTimeStamp": "Thu Jul 22 2021 13:11:03",
            "keyStrokeInfo": "",
            "position": "14,2"
        },
        {
            "operation": "TYPED",
            "lines": 0,
            "keyStrokeTimeStamp": "Thu Jul 22 2021 13:11:04",
            "keyStrokeInfo": "b",
            "position": "14,2"
        },
        {
            "operation": "TYPED",
            "lines": 0,
            "keyStrokeTimeStamp": "Thu Jul 22 2021 13:11:04",
            "keyStrokeInfo": "r",
            "position": "14,3"
        },
        {
            "operation": "TYPED",
            "lines": 0,
            "keyStrokeTimeStamp": "Thu Jul 22 2021 13:11:05",
            "keyStrokeInfo": ">",
            "position": "14,4"
        },
        {
            "operation": "DELETE",
            "lines": 0,
            "keyStrokeTimeStamp": "Thu Jul 22 2021 13:11:18",
            "keyStrokeInfo": "",
            "position": "39,52"
        },
        {
            "operation": "TYPED",
            "lines": 0,
            "keyStrokeTimeStamp": "Thu Jul 22 2021 13:11:18",
            "keyStrokeInfo": "P",
            "position": "39,52"
        },
        {
            "operation": "TYPED",
            "lines": 0,
            "keyStrokeTimeStamp": "Thu Jul 22 2021 13:11:19",
            "keyStrokeInfo": "r",
            "position": "39,53"
        },
        {
            "operation": "TYPED",
            "lines": 0,
            "keyStrokeTimeStamp": "Thu Jul 22 2021 13:11:20",
            "keyStrokeInfo": "o",
            "position": "39,54"
        },
        {
            "operation": "TYPED",
            "lines": 0,
            "keyStrokeTimeStamp": "Thu Jul 22 2021 13:11:20",
            "keyStrokeInfo": "d",
            "position": "39,55"
        },
        {
            "operation": "TYPED",
            "lines": 0,
            "keyStrokeTimeStamp": "Thu Jul 22 2021 13:11:20",
            "keyStrokeInfo": "u",
            "position": "39,56"
        },
        {
            "operation": "TYPED",
            "lines": 0,
            "keyStrokeTimeStamp": "Thu Jul 22 2021 13:11:20",
            "keyStrokeInfo": "c",
            "position": "39,57"
        },
        {
            "operation": "TYPED",
            "lines": 0,
            "keyStrokeTimeStamp": "Thu Jul 22 2021 13:11:21",
            "keyStrokeInfo": "t",
            "position": "39,58"
        },
        {
            "operation": "TYPED",
            "lines": 0,
            "keyStrokeTimeStamp": "Thu Jul 22 2021 13:11:21",
            "keyStrokeInfo": " ",
            "position": "39,59"
        },
        {
            "operation": "TYPED",
            "lines": 0,
            "keyStrokeTimeStamp": "Thu Jul 22 2021 13:11:22",
            "keyStrokeInfo": "i",
            "position": "39,60"
        },
        {
            "operation": "TYPED",
            "lines": 0,
            "keyStrokeTimeStamp": "Thu Jul 22 2021 13:11:22",
            "keyStrokeInfo": "m",
            "position": "39,61"
        },
        {
            "operation": "TYPED",
            "lines": 0,
            "keyStrokeTimeStamp": "Thu Jul 22 2021 13:11:23",
            "keyStrokeInfo": "a",
            "position": "39,62"
        },
        {
            "operation": "TYPED",
            "lines": 0,
            "keyStrokeTimeStamp": "Thu Jul 22 2021 13:11:23",
            "keyStrokeInfo": "g",
            "position": "39,63"
        },
        {
            "operation": "TYPED",
            "lines": 0,
            "keyStrokeTimeStamp": "Thu Jul 22 2021 13:11:23",
            "keyStrokeInfo": "e",
            "position": "39,64"
        },
        {
            "operation": "TYPED",
            "lines": 0,
            "keyStrokeTimeStamp": "Thu Jul 22 2021 13:11:25",
            "keyStrokeInfo": "image",
            "position": "39,60"
        }
    ]
}